defSim/Experiment.py
defSim/Simulation.py
defSim/__init__.py
defSim/agents_init/CorrelatedContinuousInitializer.py
defSim/agents_init/RandomCategoricalInitializer.py
defSim/agents_init/RandomContinuousInitializer.py
defSim/agents_init/__init__.py
defSim/agents_init/agents_init.py
defSim/dissimilarity_component/EuclideanDistance.py
defSim/dissimilarity_component/HammingDistance.py
defSim/dissimilarity_component/ManhattanDistance.py
defSim/dissimilarity_component/__init__.py
defSim/dissimilarity_component/dissimilarity_calculator.py
defSim/extensions/__init__.py
defSim/extensions/influence_sim/AcceptanceNoncommitmentRejection.py
defSim/extensions/influence_sim/Leviathan.py
defSim/extensions/influence_sim/__init__.py
defSim/extensions/tools/__init__.py
defSim/focal_agent_sim/RandomSelector.py
defSim/focal_agent_sim/__init__.py
defSim/focal_agent_sim/focal_agent_sim.py
defSim/influence_sim/BoundedConfidence.py
defSim/influence_sim/Persuasion.py
defSim/influence_sim/SimilarityAdoption.py
defSim/influence_sim/WeightedLinear.py
defSim/influence_sim/__init__.py
defSim/influence_sim/influence_sim.py
defSim/neighbor_selector_sim/RandomNeighborSelector.py
defSim/neighbor_selector_sim/SimilarNeighborSelector.py
defSim/neighbor_selector_sim/__init__.py
defSim/neighbor_selector_sim/neighbor_selector_sim.py
defSim/network_evolution_sim/MaslovSneppenModifier.py
defSim/network_evolution_sim/NewTiesModifier.py
defSim/network_evolution_sim/__init__.py
defSim/network_evolution_sim/network_evolution_sim.py
defSim/network_init/__init__.py
defSim/network_init/network_init.py
defSim/tools/ClusterExecutionScript.py
defSim/tools/ConvergenceChecks.py
defSim/tools/CreateDataFiles.py
defSim/tools/CreateOutputTable.py
defSim/tools/NetworkDistanceUpdater.py
defSim/tools/OutputMeasures.py
defSim/tools/Plots.py
defSim/tools/__init__.py
defSim-0.1.3.dist-info/LICENSE
defSim-0.1.3.dist-info/METADATA
defSim-0.1.3.dist-info/WHEEL
defSim-0.1.3.dist-info/top_level.txt
defSim-0.1.3.dist-info/RECORD
