Metadata-Version: 2.1
Name: defSim
Version: 0.1.3
Summary: The Discrete Event Framework for Social Influence Models
Home-page: https://github.com/defSim/defSim
Author: Laukemper, Keijzer, Bakker
Author-email: marijn.keijzer@iast.fr
License: GNU GPLv3
Platform: UNKNOWN
Requires-Dist: networkx (>=2.4)
Requires-Dist: numpy (>=1.17)
Requires-Dist: pandas
Requires-Dist: scipy (>=1.1.0)
Requires-Dist: tqdm (>=4.58.0)
Requires-Dist: matplotlib (>=3.1.3)
Requires-Dist: seaborn (>=0.11.1)
